c2cgeoportal_geoportal/__init__.py
c2cgeoportal_geoportal/py.typed
c2cgeoportal_geoportal/resources.py
c2cgeoportal_geoportal/lib/__init__.py
c2cgeoportal_geoportal/lib/authentication.py
c2cgeoportal_geoportal/lib/bashcolor.py
c2cgeoportal_geoportal/lib/cacheversion.py
c2cgeoportal_geoportal/lib/caching.py
c2cgeoportal_geoportal/lib/check_collector.py
c2cgeoportal_geoportal/lib/checker.py
c2cgeoportal_geoportal/lib/common_headers.py
c2cgeoportal_geoportal/lib/dbreflection.py
c2cgeoportal_geoportal/lib/filter_capabilities.py
c2cgeoportal_geoportal/lib/fulltextsearch.py
c2cgeoportal_geoportal/lib/functionality.py
c2cgeoportal_geoportal/lib/headers.py
c2cgeoportal_geoportal/lib/i18n.py
c2cgeoportal_geoportal/lib/layers.py
c2cgeoportal_geoportal/lib/lingva_extractor.py
c2cgeoportal_geoportal/lib/loader.py
c2cgeoportal_geoportal/lib/metrics.py
c2cgeoportal_geoportal/lib/oauth2.py
c2cgeoportal_geoportal/lib/oidc.py
c2cgeoportal_geoportal/lib/wmstparsing.py
c2cgeoportal_geoportal/lib/xsd.py
c2cgeoportal_geoportal/scaffolds/advance_create/cookiecutter.json
c2cgeoportal_geoportal/scaffolds/advance_create/ci/config.yaml
c2cgeoportal_geoportal/scaffolds/advance_create/{{cookiecutter.project}}/geoportal/.dockerignore
c2cgeoportal_geoportal/scaffolds/advance_create/{{cookiecutter.project}}/geoportal/.eslintrc.yaml
c2cgeoportal_geoportal/scaffolds/advance_create/{{cookiecutter.project}}/geoportal/.prospector.yaml
c2cgeoportal_geoportal/scaffolds/advance_create/{{cookiecutter.project}}/geoportal/Dockerfile
c2cgeoportal_geoportal/scaffolds/advance_create/{{cookiecutter.project}}/geoportal/Makefile
c2cgeoportal_geoportal/scaffolds/advance_create/{{cookiecutter.project}}/geoportal/alembic.ini
c2cgeoportal_geoportal/scaffolds/advance_create/{{cookiecutter.project}}/geoportal/alembic.yaml
c2cgeoportal_geoportal/scaffolds/advance_create/{{cookiecutter.project}}/geoportal/development.ini
c2cgeoportal_geoportal/scaffolds/advance_create/{{cookiecutter.project}}/geoportal/gunicorn.conf.py
c2cgeoportal_geoportal-2.9.0.388.dist-info/METADATA
c2cgeoportal_geoportal-2.9.0.388.dist-info/WHEEL
c2cgeoportal_geoportal-2.9.0.388.dist-info/entry_points.txt
c2cgeoportal_geoportal-2.9.0.388.dist-info/top_level.txt
c2cgeoportal_geoportal-2.9.0.388.dist-info/RECORD
