Metadata-Version: 2.1
Name: c2cgeoportal-geoportal
Version: 2.9.0.388
Summary: c2cgeoportal geoportal
Home-page: https://github.com/camptocamp/c2cgeoportal/
Author: Camptocamp
Author-email: info@camptocamp.com
Keywords: web gis geoportail c2cgeoportal geocommune pyramid
Classifier: Development Status :: 6 - Mature
Classifier: Environment :: Web Environment
Classifier: Framework :: Pyramid
Classifier: Intended Audience :: Other Audience
Classifier: License :: OSI Approved :: BSD License
Classifier: Operating System :: OS Independent
Classifier: Programming Language :: Python
Classifier: Programming Language :: Python :: 3
Classifier: Programming Language :: Python :: 3.12
Classifier: Topic :: Scientific/Engineering :: GIS
Classifier: Typing :: Typed
Requires-Python: >=3.10
Requires-Dist: Fiona
Requires-Dist: GeoAlchemy2
Requires-Dist: Mako
Requires-Dist: OWSLib >=0.6.0
Requires-Dist: PyYAML
Requires-Dist: SQLAlchemy
Requires-Dist: Shapely
Requires-Dist: alembic
Requires-Dist: basicauth
Requires-Dist: bottle
Requires-Dist: bs4
Requires-Dist: c2cgeoportal-commons[upgrade]
Requires-Dist: c2cwsgiutils
Requires-Dist: defusedxml
Requires-Dist: dogpile.cache >=0.6
Requires-Dist: geojson
Requires-Dist: isodate
Requires-Dist: lingva
Requires-Dist: papyrus
Requires-Dist: pkce
Requires-Dist: psycopg2
Requires-Dist: pycryptodome
Requires-Dist: pyotp
Requires-Dist: pyramid
Requires-Dist: pyramid-debugtoolbar
Requires-Dist: pyramid-mako
Requires-Dist: pyramid-multiauth
Requires-Dist: pyramid-tm
Requires-Dist: python-dateutil
Requires-Dist: rasterio
Requires-Dist: redis
Requires-Dist: requests
Requires-Dist: setuptools >=78.1.1
Requires-Dist: simple-openid-connect
Requires-Dist: tilecloud
Requires-Dist: transaction
